{
    "color_1": "#0dd37c",
    "color_2": "#00477e",
    "color_3": "#8fd998",
    "color_4": "#be2d09",
    "color_5": "#b305f0",
    "color_6": "#1c2fe4",
    "color_7": "#aad72f",
    "color_8": "#48149d",
    "color_9": "#d8bf0d",
    "color_10": "#e71400",
    "color_11": "#899a04",
    "color_12": "#082e44",
    "color_13": "#4c8c75",
    "color_14": "#50e7d9",
    "color_15": "#fa4682",
    "color_16": "#3aad54",
    "color_17": "#c5e501",
    "color_18": "#f6bd89",
    "color_19": "#4c8994",
    "color_20": "#43a82f",
    "color_21": "#937672",
    "color_22": "#785678",
    "color_23": "#4df64a",
    "color_24": "#a98d2e",
    "color_25": "#c3e917",
    "color_26": "#81a3b5",
    "color_27": "#26d2a4",
    "color_28": "#b230e1",
    "color_29": "#46b677",
    "color_30": "#31500d",
    "color_31": "#efb9ac",
    "color_32": "#2f5749",
    "color_33": "#980dac",
    "color_34": "#28a4d3",
    "color_35": "#87584b",
    "color_36": "#f7e363",
    "color_37": "#51b793",
    "color_38": "#e621c9",
    "color_39": "#50205d",
    "color_40": "#f3ba9f",
    "color_41": "#522a61",
    "color_42": "#3c02d0",
    "color_43": "#104960",
    "color_44": "#cc5254",
    "color_45": "#96e39b",
    "color_46": "#7f67eb",
    "color_47": "#7691fa",
    "color_48": "#784fee",
    "color_49": "#4bf906",
    "color_50": "#e11656",
    "color_51": "#e83c23",
    "color_52": "#0cabd5",
    "color_53": "#9e2dca",
    "color_54": "#7182e1",
    "color_55": "#ae033f",
    "color_56": "#55efe4",
    "color_57": "#e21d8d",
    "color_58": "#0d6c45",
    "color_59": "#879ce8",
    "color_60": "#08796a",
    "color_61": "#416137",
    "color_62": "#9d8f6f",
    "color_63": "#958125",
    "color_64": "#76c968",
    "color_65": "#d10991",
    "color_66": "#af5bff",
    "color_67": "#2543b4",
    "color_68": "#69529f",
    "color_69": "#9f0df1",
    "color_70": "#14a923",
    "color_71": "#cf8d53",
    "color_72": "#a7407e",
    "color_73": "#f41538",
    "color_74": "#bb81df",
    "color_75": "#e772ee",
    "color_76": "#22332c",
    "color_77": "#3aee19",
    "color_78": "#0a2c68",
    "color_79": "#907522",
    "color_80": "#c5b4e1",
    "color_81": "#19c652",
    "color_82": "#52a6ce",
    "color_83": "#d96d40",
    "color_84": "#2d37f1",
    "color_85": "#ef5563",
    "color_86": "#ffbe8f",
    "color_87": "#dbdf64",
    "color_88": "#3fc08b",
    "color_89": "#f3864f",
    "color_90": "#1db0d1",
    "color_91": "#b069e8",
    "color_92": "#f2294f",
    "color_93": "#935555",
    "color_94": "#f6848c",
    "color_95": "#801659",
    "color_96": "#10de8c",
    "color_97": "#6b2ac5",
    "color_98": "#d45460",
    "color_99": "#ec5df1",
    "color_100": "#2bf11b",
    "color_101": "#382823",
    "color_102": "#dda140",
    "color_103": "#353105",
    "color_104": "#df826b",
    "color_105": "#c84baf",
    "color_106": "#31836e",
    "color_107": "#eda261",
    "color_108": "#9655c3",
    "color_109": "#306479",
    "color_110": "#571dca",
    "color_111": "#1b0d2e",
    "color_112": "#2522e4",
    "color_113": "#06c8cc",
    "color_114": "#7ced0a",
    "color_115": "#266d40",
    "color_116": "#59a0d3",
    "color_117": "#4cdfaa",
    "color_118": "#78ebc0",
    "color_119": "#db3dd3",
    "color_120": "#50b519",
    "color_121": "#dad42d",
    "color_122": "#35029d",
    "color_123": "#55c957",
    "color_124": "#5d2a72",
    "color_125": "#18e42e",
    "color_126": "#078e52",
    "color_127": "#0e329e",
    "color_128": "#2b0f04",
    "color_129": "#e491f4",
    "color_130": "#229815",
    "color_131": "#da1029",
    "color_132": "#c39a47",
    "color_133": "#fe056a",
    "color_134": "#4873cc",
    "color_135": "#a1a831",
    "color_136": "#32d9f3",
    "color_137": "#cd7f49",
    "color_138": "#f6c36d",
    "color_139": "#e7e4ec",
    "color_140": "#44d52a",
    "color_141": "#beb31f",
    "color_142": "#340fe7",
    "color_143": "#4327e5",
    "color_144": "#361a50",
    "color_145": "#c9006a",
    "color_146": "#3c1955",
    "color_147": "#b42c03",
    "color_148": "#ba2647",
    "color_149": "#068dac",
    "color_150": "#02633d",
    "color_151": "#7774d2",
    "color_152": "#1f34ca",
    "color_153": "#4837ad",
    "color_154": "#16af26",
    "color_155": "#527f09",
    "color_156": "#5c41d1",
    "color_157": "#0d539b",
    "color_158": "#84d2e5",
    "color_159": "#f35932",
    "color_160": "#bed7ae",
    "color_161": "#c937e0",
    "color_162": "#2598c6",
    "color_163": "#ab0a9b",
    "color_164": "#ac2761",
    "color_165": "#5addfe",
    "color_166": "#1ebf41",
    "color_167": "#821007",
    "color_168": "#d64efd",
    "color_169": "#70911f",
    "color_170": "#783cc7",
    "color_171": "#95cc6c",
    "color_172": "#1a4903",
    "color_173": "#bcbe9a",
    "color_174": "#be1c08",
    "color_175": "#e76074",
    "color_176": "#ef85be",
    "color_177": "#f0590b",
    "color_178": "#d566a2",
    "color_179": "#48dcc0",
    "color_180": "#05d477",
    "color_181": "#1febe4",
    "color_182": "#0e5f6e",
    "color_183": "#f468be",
    "color_184": "#4fafc7",
    "color_185": "#63c41f",
    "color_186": "#cf5960",
    "color_187": "#391c12",
    "color_188": "#188daf",
    "color_189": "#52b94a",
    "color_190": "#3e0ea4",
    "color_191": "#47e318",
    "color_192": "#840d11",
    "color_193": "#5d6504",
    "color_194": "#7c07fc",
    "color_195": "#9a0b08",
    "color_196": "#26b6c5",
    "color_197": "#35d480",
    "color_198": "#fcc306",
    "color_199": "#033185",
    "color_200": "#a6a10c",
    "color_201": "#1e7f1d",
    "color_202": "#d919f1",
    "color_203": "#36bb47",
    "color_204": "#2edea1",
    "color_205": "#7a0440",
    "color_206": "#88fac7",
    "color_207": "#a968c8",
    "color_208": "#d672c7",
    "color_209": "#367a7e",
    "color_210": "#14908d",
    "color_211": "#fabc3a",
    "color_212": "#54bf47",
    "color_213": "#c86768",
    "color_214": "#97e52f",
    "color_215": "#79e14b",
    "color_216": "#100919",
    "color_217": "#afbefa",
    "color_218": "#ecbfc9",
    "color_219": "#77cb9f",
    "color_220": "#ca498d",
    "color_221": "#da4615",
    "color_222": "#590d0a",
    "color_223": "#0de37b",
    "color_224": "#667fb5",
    "color_225": "#1e8aae",
    "color_226": "#457336",
    "color_227": "#7082c7",
    "color_228": "#20ba60",
    "color_229": "#838a2f",
    "color_230": "#765bfd",
    "color_231": "#6556a4",
    "color_232": "#6c8b2e",
    "color_233": "#1642d2",
    "color_234": "#de2790",
    "color_235": "#e42fc3",
    "color_236": "#049bc8",
    "color_237": "#e95896",
    "color_238": "#bb94aa",
    "color_239": "#7cf059",
    "color_240": "#329347",
    "color_241": "#262eea",
    "color_242": "#776224",
    "color_243": "#224c9a",
    "color_244": "#982357",
    "color_245": "#f9291d",
    "color_246": "#4106bd",
    "color_247": "#9f87d1",
    "color_248": "#ff93c9",
    "color_249": "#1aeb78",
    "color_250": "#3f2175",
    "color_251": "#6068fe",
    "color_252": "#dd06ce",
    "color_253": "#6ce2ff",
    "color_254": "#28779f",
    "color_255": "#272262",
    "color_256": "#523ef4",
    "color_257": "#dc1064",
    "color_258": "#07286f",
    "color_259": "#4ea66c",
    "color_260": "#cab722",
    "color_261": "#ddeb21",
    "color_262": "#129a8d",
    "color_263": "#6b6830",
    "color_264": "#8c7993",
    "color_265": "#4432cb",
    "color_266": "#0a4049",
    "color_267": "#b11c7d",
    "color_268": "#02b735",
    "color_269": "#0b5ca5",
    "color_270": "#d1a0d4",
    "color_271": "#91a010",
    "color_272": "#a2f86b",
    "color_273": "#f11b98",
    "color_274": "#5c3e7d",
    "color_275": "#7ecde7",
    "color_276": "#613030",
    "color_277": "#da5840",
    "color_278": "#a76ba5",
    "color_279": "#0dbcbe",
    "color_280": "#0c3cdb",
    "color_281": "#731a94",
    "color_282": "#7a174b",
    "color_283": "#c66464",
    "color_284": "#5be499",
    "color_285": "#746cd7",
    "color_286": "#8bd1b8",
    "color_287": "#d6bcb9",
    "color_288": "#d994d6",
    "color_289": "#e5cd5e",
    "color_290": "#4bf840",
    "color_291": "#66852f",
    "color_292": "#dd941b",
    "color_293": "#c36f5c",
    "color_294": "#f64f22",
    "color_295": "#11c97c",
    "color_296": "#d349e5",
    "color_297": "#6bf5c0",
    "color_298": "#fcc92b",
    "color_299": "#f69caf",
    "color_300": "#979e18",
    "color_301": "#c788a3",
    "color_302": "#91414b",
    "color_303": "#f11e9e",
    "color_304": "#2b638e",
    "color_305": "#29c0c7",
    "color_306": "#5dd5cc",
    "color_307": "#5dcb65",
    "color_308": "#70a028",
    "color_309": "#478dce",
    "color_310": "#1b567c",
    "color_311": "#bc957d",
    "color_312": "#ea9c07",
    "color_313": "#9dadfc",
    "color_314": "#279f24",
    "color_315": "#c574e0",
    "color_316": "#6ff0e0",
    "color_317": "#24bf16",
    "color_318": "#2e310c",
    "color_319": "#ab9384",
    "color_320": "#5dfce3",
    "color_321": "#e76d05",
    "color_322": "#474013",
    "color_323": "#de7b80",
    "color_324": "#f281a9",
    "color_325": "#d460a3",
    "color_326": "#222d3b",
    "color_327": "#7fbbce",
    "color_328": "#42e999",
    "color_329": "#dfccf0",
    "color_330": "#2ab791",
    "color_331": "#7a1060",
    "color_332": "#5540d3",
    "color_333": "#a28ca4",
    "color_334": "#d16fa1",
    "color_335": "#e9ce00",
    "color_336": "#4e632c",
    "color_337": "#d4b030",
    "color_338": "#5a35df",
    "color_339": "#0c89de",
    "color_340": "#a6619f",
    "color_341": "#09bb0b",
    "color_342": "#de18da",
    "color_343": "#9d84f5",
    "color_344": "#8e75a1",
    "color_345": "#9cc73e",
    "color_346": "#81dd02",
    "color_347": "#55c9c2",
    "color_348": "#4e7c9c",
    "color_349": "#3a919c",
    "color_350": "#bad832",
    "color_351": "#819219",
    "color_352": "#60c10c",
    "color_353": "#31d84b",
    "color_354": "#7c9655",
    "color_355": "#fb11f4",
    "color_356": "#17101b",
    "color_357": "#8bccbc",
    "color_358": "#712849",
    "color_359": "#6aacda",
    "color_360": "#da707e",
    "color_361": "#bb03fd",
    "color_362": "#4e702c",
    "color_363": "#e7f509",
    "color_364": "#8fe74b",
    "color_365": "#41f9a5",
    "color_366": "#dbb062",
    "color_367": "#a19729",
    "color_368": "#5aed1d",
    "color_369": "#8a4986",
    "color_370": "#380311",
    "color_371": "#9448c3",
    "color_372": "#3e4c56",
    "color_373": "#23248a",
    "color_374": "#53c7b8",
    "color_375": "#f14c20",
    "color_376": "#48d875",
    "color_377": "#f74f11",
    "color_378": "#f28f51",
    "color_379": "#7ae3ee",
    "color_380": "#d7ad8f",
    "color_381": "#c342aa",
    "color_382": "#4f2386",
    "color_383": "#92e77b",
    "color_384": "#c7adc7",
    "color_385": "#314d0a",
    "color_386": "#96abf0",
    "color_387": "#02b1bd",
    "color_388": "#9bdf0b",
    "color_389": "#a90971",
    "color_390": "#536602",
    "color_391": "#24a8c7",
    "color_392": "#b31a6c",
    "color_393": "#0fcf05",
    "color_394": "#74b355",
    "color_395": "#1e8380",
    "color_396": "#9c970f",
    "color_397": "#37de6f",
    "color_398": "#583c7d",
    "color_399": "#9c6fd9",
    "color_400": "#9e87ca",
    "color_401": "#91b15a",
    "color_402": "#e27e32",
    "color_403": "#d5f632",
    "color_404": "#8e1582",
    "color_405": "#07fa2c",
    "color_406": "#dc4947",
    "color_407": "#735d0c",
    "color_408": "#58f44f",
    "color_409": "#6d8e18",
    "color_410": "#df96ac",
    "color_411": "#eeb48d",
    "color_412": "#9a3098",
    "color_413": "#7d5ddb",
    "color_414": "#5f0fa5",
    "color_415": "#e9db68",
    "color_416": "#221245",
    "color_417": "#cd87c5",
    "color_418": "#905fa6",
    "color_419": "#f60ae8",
    "color_420": "#eac9ba",
    "color_421": "#72d04e",
    "color_422": "#86430f",
    "color_423": "#311c1f",
    "color_424": "#b82e3f",
    "color_425": "#c27f33",
    "color_426": "#2c1530",
    "color_427": "#a72c41",
    "color_428": "#580795",
    "color_429": "#b0956c",
    "color_430": "#a62202",
    "color_431": "#5d3764",
    "color_432": "#23e273",
    "color_433": "#f1c39e",
    "color_434": "#e1c8c7",
    "color_435": "#ef2ded",
    "color_436": "#0eb893",
    "color_437": "#f4eed1",
    "color_438": "#2d38c3",
    "color_439": "#1d805f",
    "color_440": "#63c8ca",
    "color_441": "#9b8ddb",
    "color_442": "#56fcb3",
    "color_443": "#6bfdf8",
    "color_444": "#0a6820",
    "color_445": "#2f0fd4",
    "color_446": "#faa9c6",
    "color_447": "#ef78ed",
    "color_448": "#74820e",
    "color_449": "#016843",
    "color_450": "#474bfc",
    "color_451": "#25fdd2",
    "color_452": "#5f595c",
    "color_453": "#f2122a",
    "color_454": "#209e02",
    "color_455": "#d91aa9",
    "color_456": "#6c2b76",
    "color_457": "#2f270f",
    "color_458": "#07dff6",
    "color_459": "#695e04",
    "color_460": "#a95516",
    "color_461": "#8639a2",
    "color_462": "#778a70",
    "color_463": "#70c598",
    "color_464": "#60f17a",
    "color_465": "#3e4514",
    "color_466": "#97d33c",
    "color_467": "#1fcf51",
    "color_468": "#1a212f",
    "color_469": "#4b04dc",
    "color_470": "#cfe0e8",
    "color_471": "#c43dff",
    "color_472": "#c811b0",
    "color_473": "#b9e162",
    "color_474": "#cd5c00",
    "color_475": "#3ec0b8",
    "color_476": "#36e617",
    "color_477": "#4a141e",
    "color_478": "#96fd0f",
    "color_479": "#14a5d3",
    "color_480": "#a1c567",
    "color_481": "#bf37c5",
    "color_482": "#64cdca",
    "color_483": "#398495",
    "color_484": "#1fdd5a",
    "color_485": "#0d58b2",
    "color_486": "#3ef056",
    "color_487": "#e28eda",
    "color_488": "#e8cdd5",
    "color_489": "#e68694",
    "color_490": "#d6f254",
    "color_491": "#b78586",
    "color_492": "#2f7f56",
    "color_493": "#df4b2e",
    "color_494": "#dddade",
    "color_495": "#992ef4",
    "color_496": "#ac938f",
    "color_497": "#8f2416",
    "color_498": "#2e60eb",
    "color_499": "#79cdd5",
    "color_500": "#ed5faa",
    "color_501": "#1f26aa",
    "color_502": "#8be21c",
    "color_503": "#17212c",
    "color_504": "#11494b",
    "color_505": "#a22162",
    "color_506": "#f1789b",
    "color_507": "#a25e79",
    "color_508": "#628876",
    "color_509": "#873c48",
    "color_510": "#6b359c",
    "color_511": "#596d85",
    "color_512": "#8609d4",
    "color_513": "#1e4653",
    "color_514": "#8c12c9",
    "color_515": "#6b9c8d",
    "color_516": "#383a39",
    "color_517": "#434e2d",
    "color_518": "#08405c",
    "color_519": "#c55108",
    "color_520": "#d834a9",
    "color_521": "#b8af92",
    "color_522": "#536a5c",
    "color_523": "#c0b2eb",
    "color_524": "#ff17db",
    "color_525": "#db577e",
    "color_526": "#4ad1ea",
    "color_527": "#c542d9",
    "color_528": "#30b2d3",
    "color_529": "#e77c01",
    "color_530": "#f62ccd",
    "color_531": "#0a33e4",
    "color_532": "#861ba2",
    "color_533": "#15049f",
    "color_534": "#778b9d",
    "color_535": "#6faa1d",
    "color_536": "#031ffe",
    "color_537": "#5d2968",
    "color_538": "#a3490d",
    "color_539": "#192611",
    "color_540": "#61193d",
    "color_541": "#97249f",
    "color_542": "#549b2c",
    "color_543": "#521658",
    "color_544": "#b89c8e",
    "color_545": "#1af2cd",
    "color_546": "#4861f7",
    "color_547": "#2171fc",
    "color_548": "#f577e6",
    "color_549": "#fb2741",
    "color_550": "#8b247c",
    "color_551": "#859a79",
    "color_552": "#5b46ca",
    "color_553": "#b38abc",
    "color_554": "#a42b71",
    "color_555": "#926c14",
    "color_556": "#8bf7fa",
    "color_557": "#e2b722",
    "color_558": "#bdb5d0",
    "color_559": "#6b6225",
    "color_560": "#18c677",
    "color_561": "#269afe",
    "color_562": "#34dc2f",
    "color_563": "#b98254",
    "color_564": "#27f06d",
    "color_565": "#b86be9",
    "color_566": "#e07618",
    "color_567": "#8b9371",
    "color_568": "#b7f8af",
    "color_569": "#2a3e48",
    "color_570": "#854083",
    "color_571": "#e90c4d",
    "color_572": "#cf72e4",
    "color_573": "#a64658",
    "color_574": "#283c06",
    "color_575": "#c84a99",
    "color_576": "#8ec8f2",
    "color_577": "#f27644",
    "color_578": "#6828e3",
    "color_579": "#87094d",
    "color_580": "#508413",
    "color_581": "#097dbd",
    "color_582": "#e10f3e",
    "color_583": "#ecddd3",
    "color_584": "#02b422",
    "color_585": "#9998e0",
    "color_586": "#289cad",
    "color_587": "#07f903",
    "color_588": "#d7e503",
    "color_589": "#48a84c",
    "color_590": "#813b49",
    "color_591": "#78275c",
    "color_592": "#d87385",
    "color_593": "#626f67",
    "color_594": "#3da464",
    "color_595": "#33ba0c",
    "color_596": "#13f5a2",
    "color_597": "#ca4057",
    "color_598": "#286f77",
    "color_599": "#b224f1",
    "color_600": "#7bca89",
    "color_601": "#cc5f8d",
    "color_602": "#70e771",
    "color_603": "#e432c1",
    "color_604": "#ec34f4",
    "color_605": "#17bcdc",
    "color_606": "#bcb22d",
    "color_607": "#03cbb1",
    "color_608": "#02eec3",
    "color_609": "#d60710",
    "color_610": "#05ef9f",
    "color_611": "#ed16ad",
    "color_612": "#989998",
    "color_613": "#2856b4",
    "color_614": "#e44949",
    "color_615": "#d4e9fd",
    "color_616": "#59c074",
    "color_617": "#dad223",
    "color_618": "#096995",
    "color_619": "#2a66df",
    "color_620": "#869018",
    "color_621": "#d1bafc",
    "color_622": "#edb300",
    "color_623": "#e3eab8",
    "color_624": "#a45d8a",
    "color_625": "#c3fb88",
    "color_626": "#49f842",
    "color_627": "#869b7b",
    "color_628": "#8a6641",
    "color_629": "#24962a",
    "color_630": "#42f559",
    "color_631": "#e13c34",
    "color_632": "#d0ec2a",
    "color_633": "#b9f06c",
    "color_634": "#3e8716",
    "color_635": "#6fa0d7",
    "color_636": "#160a44",
    "color_637": "#43f8c6",
    "color_638": "#1009f0",
    "color_639": "#10c150",
    "color_640": "#0e1206",
    "color_641": "#42bd8c",
    "color_642": "#28a596",
    "color_643": "#d2902e",
    "color_644": "#b8321d",
    "color_645": "#8f91ff",
    "color_646": "#b28cca",
    "color_647": "#866120",
    "color_648": "#1fc824",
    "color_649": "#ed2bad",
    "color_650": "#ea9547",
    "color_651": "#f2b95e",
    "color_652": "#9f098c",
    "color_653": "#da35fe",
    "color_654": "#2ec490",
    "color_655": "#d1152d",
    "color_656": "#67ae0e",
    "color_657": "#4e1f01",
    "color_658": "#bb6b8c",
    "color_659": "#7c127a",
    "color_660": "#140ea5",
    "color_661": "#370dec",
    "color_662": "#2f4cb5",
    "color_663": "#c1388a",
    "color_664": "#dc3eff",
    "color_665": "#02c2ea",
    "color_666": "#8ea7f4",
    "color_667": "#2a7f1b",
    "color_668": "#befd4d",
    "color_669": "#1b5483",
    "color_670": "#8c991d",
    "color_671": "#e7b389",
    "color_672": "#6fbf09",
    "color_673": "#66022f",
    "color_674": "#261960",
    "color_675": "#585087",
    "color_676": "#8a8677",
    "color_677": "#79d37a",
    "color_678": "#11eb95",
    "color_679": "#998fc7",
    "color_680": "#73195f",
    "color_681": "#a62781",
    "color_682": "#36a617",
    "color_683": "#e57414",
    "color_684": "#8622be",
    "color_685": "#497536",
    "color_686": "#1245ec",
    "color_687": "#ef8f48",
    "color_688": "#d336f3",
    "color_689": "#87277a",
    "color_690": "#7a0a7b",
    "color_691": "#35da5f",
    "color_692": "#01ae7a",
    "color_693": "#a99be4",
    "color_694": "#982335",
    "color_695": "#4905a2",
    "color_696": "#a8b858",
    "color_697": "#199eb1",
    "color_698": "#5f541d",
    "color_699": "#54090b",
    "color_700": "#2dbc0a",
    "color_701": "#0d1148",
    "color_702": "#d59fab",
    "color_703": "#5af82c",
    "color_704": "#37700d",
    "color_705": "#61bcd5",
    "color_706": "#b904e3",
    "color_707": "#3b5d7b",
    "color_708": "#32ee09",
    "color_709": "#c674d8",
    "color_710": "#b2f52d",
    "color_711": "#33d35c",
    "color_712": "#4a5d6b",
    "color_713": "#e3439c",
    "color_714": "#1422db",
    "color_715": "#3829b7",
    "color_716": "#4caa84",
    "color_717": "#34cc6e",
    "color_718": "#8ef0dd",
    "color_719": "#4c4f8d",
    "color_720": "#05f83b",
    "color_721": "#0968d2",
    "color_722": "#58f2ae",
    "color_723": "#65e63c",
    "color_724": "#09c2b6",
    "color_725": "#7d5ebb",
    "color_726": "#fdd29a",
    "color_727": "#2d7a4d",
    "color_728": "#4d1932",
    "color_729": "#a0cede",
    "color_730": "#66e442",
    "color_731": "#13b219",
    "color_732": "#184b58",
    "color_733": "#c8df12",
    "color_734": "#126a27",
    "color_735": "#6ad458",
    "color_736": "#e5daa4",
    "color_737": "#793371",
    "color_738": "#9350b5",
    "color_739": "#6d89fa",
    "color_740": "#3372b1",
    "color_741": "#02ecc0",
    "color_742": "#02722c",
    "color_743": "#e63b6c",
    "color_744": "#78f276",
    "color_745": "#16a3fc",
    "color_746": "#afc4ee",
    "color_747": "#3d78aa",
    "color_748": "#449899",
    "color_749": "#3caf54",
    "color_750": "#66d0bf",
    "color_751": "#920070",
    "color_752": "#107923",
    "color_753": "#279d0f",
    "color_754": "#6883bc",
    "color_755": "#4fd76b",
    "color_756": "#6e155c",
    "color_757": "#1647b6",
    "color_758": "#912b5d",
    "color_759": "#33e815",
    "color_760": "#ec3297",
    "color_761": "#1376c5",
    "color_762": "#c14ff3",
    "color_763": "#75f8a4",
    "color_764": "#5b29a9",
    "color_765": "#0d4a8a",
    "color_766": "#7d223f",
    "color_767": "#920d2d",
    "color_768": "#8a2660",
    "color_769": "#3cf6a6",
    "color_770": "#76e52d",
    "color_771": "#c1666a",
    "color_772": "#884c3b",
    "color_773": "#c3d766",
    "color_774": "#7d3ac1",
    "color_775": "#a905cd",
    "color_776": "#83024a",
    "color_777": "#761fa8",
    "color_778": "#7dea98",
    "color_779": "#7c144c",
    "color_780": "#13c762",
    "color_781": "#cb8ef2",
    "color_782": "#a13c60",
    "color_783": "#9a8cef",
    "color_784": "#6db260",
    "color_785": "#219c31",
    "color_786": "#88c0c1",
    "color_787": "#0399a5",
    "color_788": "#d77e3d",
    "color_789": "#8c71c2",
    "color_790": "#7d59ed",
    "color_791": "#8ced78",
    "color_792": "#2254c1",
    "color_793": "#07b9b7",
    "color_794": "#5bd264",
    "color_795": "#a9eecb",
    "color_796": "#7de9f0",
    "color_797": "#12d985",
    "color_798": "#4c2b41",
    "color_799": "#0272fc",
    "color_800": "#a894a7",
    "color_801": "#74ea7b",
    "color_802": "#f5c5e1",
    "color_803": "#7008d1",
    "color_804": "#1df9a1",
    "color_805": "#b97860",
    "color_806": "#c7f6d3",
    "color_807": "#cc3876",
    "color_808": "#1b288e",
    "color_809": "#815d64",
    "color_810": "#f965ef",
    "color_811": "#dd67a4",
    "color_812": "#d8b607",
    "color_813": "#c24606",
    "color_814": "#8015eb",
    "color_815": "#92250d",
    "color_816": "#e82069",
    "color_817": "#44a648",
    "color_818": "#457e1f",
    "color_819": "#a18878",
    "color_820": "#1a0dad",
    "color_821": "#6d9b35",
    "color_822": "#267a20",
    "color_823": "#1d78b6",
    "color_824": "#376ff9",
    "color_825": "#c471fd",
    "color_826": "#aae98a",
    "color_827": "#a52662",
    "color_828": "#ad890e",
    "color_829": "#57b460",
    "color_830": "#6d1f4a",
    "color_831": "#d59ef9",
    "color_832": "#bfedc5",
    "color_833": "#7592e3",
    "color_834": "#42ce58",
    "color_835": "#9b95b8",
    "color_836": "#b2fc4a",
    "color_837": "#33d732",
    "color_838": "#6f13d3",
    "color_839": "#fedf2e",
    "color_840": "#c9fcc9",
    "color_841": "#5f832c",
    "color_842": "#e6a835",
    "color_843": "#92af2d",
    "color_844": "#5bbe10",
    "color_845": "#427526",
    "color_846": "#86b47e",
    "color_847": "#a23cd6",
    "color_848": "#6e152e",
    "color_849": "#28e597",
    "color_850": "#bd94ff",
    "color_851": "#09df3b",
    "color_852": "#52b3bf",
    "color_853": "#9c0d72",
    "color_854": "#f9e32f",
    "color_855": "#16261c",
    "color_856": "#1afb35",
    "color_857": "#fd5ad2",
    "color_858": "#f65663",
    "color_859": "#b0d6ec",
    "color_860": "#ee5516",
    "color_861": "#3b28c2",
    "color_862": "#4ef1c6",
    "color_863": "#2fd8e8",
    "color_864": "#3d4a6a",
    "color_865": "#4fddf6",
    "color_866": "#d1ccc4",
    "color_867": "#40e609",
    "color_868": "#41770f",
    "color_869": "#79fd28",
    "color_870": "#a7d238",
    "color_871": "#31d129",
    "color_872": "#e22390",
    "color_873": "#786902",
    "color_874": "#3f8107",
    "color_875": "#1df334",
    "color_876": "#7e28fe",
    "color_877": "#b32179",
    "color_878": "#66fab6",
    "color_879": "#47e866",
    "color_880": "#aaa116",
    "color_881": "#9e845c",
    "color_882": "#bb2426",
    "color_883": "#7beb00",
    "color_884": "#ef404d",
    "color_885": "#93750d",
    "color_886": "#f0fa06",
    "color_887": "#2e48f0",
    "color_888": "#262383",
    "color_889": "#e41ac0",
    "color_890": "#0499d5",
    "color_891": "#13a6db",
    "color_892": "#e465eb",
    "color_893": "#5f1b50",
    "color_894": "#9838fd",
    "color_895": "#81cb78",
    "color_896": "#7f168c",
    "color_897": "#f0f5a3",
    "color_898": "#3b0d75",
    "color_899": "#90028e",
    "color_900": "#e3e23f",
    "color_901": "#365050",
    "color_902": "#bc854a",
    "color_903": "#855525",
    "color_904": "#55a4dc",
    "color_905": "#eed735",
    "color_906": "#93ec8f",
    "color_907": "#6a7f2b",
    "color_908": "#1294dd",
    "color_909": "#b9f89c",
    "color_910": "#a67977",
    "color_911": "#64b924",
    "color_912": "#42da5e",
    "color_913": "#5c13ba",
    "color_914": "#4df08c",
    "color_915": "#8cc676",
    "color_916": "#7d8c72",
    "color_917": "#7dadec",
    "color_918": "#db2b80",
    "color_919": "#0df1b7",
    "color_920": "#1b251f",
    "color_921": "#4254a2",
    "color_922": "#643360",
    "color_923": "#851032",
    "color_924": "#2b3bd5",
    "color_925": "#fb0beb",
    "color_926": "#3a3e81",
    "color_927": "#b6502a",
    "color_928": "#503a17",
    "color_929": "#81040c",
    "color_930": "#c862b7",
    "color_931": "#f376d0",
    "color_932": "#22e298",
    "color_933": "#d9fcbd",
    "color_934": "#31f759",
    "color_935": "#ecec45",
    "color_936": "#be6fa4",
    "color_937": "#d1c1d6",
    "color_938": "#cc72fe",
    "color_939": "#2be834",
    "color_940": "#93e16c",
    "color_941": "#87bee3",
    "color_942": "#23e5df",
    "color_943": "#eb0c95",
    "color_944": "#14eb07",
    "color_945": "#365fef",
    "color_946": "#59d530",
    "color_947": "#894a2b",
    "color_948": "#6a82a9",
    "color_949": "#978d6e",
    "color_950": "#9b949c",
    "color_951": "#1d791c",
    "color_952": "#ad8ac9",
    "color_953": "#2174ff",
    "color_954": "#cd8413",
    "color_955": "#49f4b3",
    "color_956": "#8f8681",
    "color_957": "#8bf99a",
    "color_958": "#409662",
    "color_959": "#fe914b",
    "color_960": "#b29805",
    "color_961": "#56705b",
    "color_962": "#5d84b7",
    "color_963": "#e6bd7c",
    "color_964": "#624637",
    "color_965": "#b16a7d",
    "color_966": "#1a70a1",
    "color_967": "#08f535",
    "color_968": "#5cd420",
    "color_969": "#37098e",
    "color_970": "#6d2a07",
    "color_971": "#4903b7",
    "color_972": "#3eb41d",
    "color_973": "#6bcd3f",
    "color_974": "#803957",
    "color_975": "#c35de3",
    "color_976": "#9f79d5",
    "color_977": "#92cf93",
    "color_978": "#d69b8e",
    "color_979": "#b52181",
    "color_980": "#6e7095",
    "color_981": "#e0f42b",
    "color_982": "#d00241",
    "color_983": "#3d5af5",
    "color_984": "#b8fea1",
    "color_985": "#152cb1",
    "color_986": "#2bd4cc",
    "color_987": "#bb4842",
    "color_988": "#750a7f",
    "color_989": "#b68f32",
    "color_990": "#66b9ae",
    "color_991": "#97c743",
    "color_992": "#a6c55e",
    "color_993": "#f83ab6",
    "color_994": "#f1c136",
    "color_995": "#d17ae4",
    "color_996": "#afc5ae",
    "color_997": "#0679ba",
    "color_998": "#de3718",
    "color_999": "#e54a77",
    "color_1000": "#be0dd8"
}